appezztp/__init__.py
appezztp/vtg_ezztp_inertia_register_tbm_.py
appezztp/z_core.py
appezztp/z_main.py
TuesdayZTP-0.8.7.dist-info/LICENSE.txt
TuesdayZTP-0.8.7.dist-info/METADATA
TuesdayZTP-0.8.7.dist-info/WHEEL
TuesdayZTP-0.8.7.dist-info/top_level.txt
TuesdayZTP-0.8.7.dist-info/RECORD
