Metadata-Version: 2.1
Name: TuesdayZTP
Version: 0.8.7
Summary: A GUI for register of ZTP
Home-page: https://github.com/chenchaotsun/scripts
Author: Chaoqun Chen
Author-email: chen.chaoqun.ext@99cloud.net
License: GNU General Public License v3.0
Project-URL: Bug Tracker, https://github.com/pypa/sampleproject/issues
Keywords: easyztp
Platform: UNKNOWN
Classifier: Programming Language :: Python :: 2
Classifier: License :: OSI Approved :: GNU General Public License v3 (GPLv3)
Classifier: Operating System :: OS Independent
Requires-Python: >=2.6
